<?xml version="1.0" encoding="UTF-8"?>
<metadata xml:lang="es"><Esri><CreaDate>20260306</CreaDate><CreaTime>17145700</CreaTime><ArcGISFormat>1.0</ArcGISFormat><SyncOnce>TRUE</SyncOnce><DataProperties><lineage><Process ToolSource="d:\program files (x86)\arcgis\desktop10.8\ArcToolbox\Toolboxes\Spatial Analyst Tools.tbx\CellStatistics" Date="20260306" Time="171457">CellStatistics D:\2026-ARTICULOS\IA-INDICE_SEQUIA\BALANCE1\BH_1960.tif;D:\2026-ARTICULOS\IA-INDICE_SEQUIA\BALANCE1\BH_1961.tif;D:\2026-ARTICULOS\IA-INDICE_SEQUIA\BALANCE1\BH_1962.tif;D:\2026-ARTICULOS\IA-INDICE_SEQUIA\BALANCE1\BH_1963.tif;D:\2026-ARTICULOS\IA-INDICE_SEQUIA\BALANCE1\BH_1964.tif;D:\2026-ARTICULOS\IA-INDICE_SEQUIA\BALANCE1\BH_1965.tif;D:\2026-ARTICULOS\IA-INDICE_SEQUIA\BALANCE1\BH_1966.tif;D:\2026-ARTICULOS\IA-INDICE_SEQUIA\BALANCE1\BH_1967.tif;D:\2026-ARTICULOS\IA-INDICE_SEQUIA\BALANCE1\BH_1968.tif;D:\2026-ARTICULOS\IA-INDICE_SEQUIA\BALANCE1\BH_1969.tif;D:\2026-ARTICULOS\IA-INDICE_SEQUIA\BALANCE1\BH_1970.tif;D:\2026-ARTICULOS\IA-INDICE_SEQUIA\BALANCE1\BH_1971.tif;D:\2026-ARTICULOS\IA-INDICE_SEQUIA\BALANCE1\BH_1972.tif;D:\2026-ARTICULOS\IA-INDICE_SEQUIA\BALANCE1\BH_1973.tif;D:\2026-ARTICULOS\IA-INDICE_SEQUIA\BALANCE1\BH_1974.tif;D:\2026-ARTICULOS\IA-INDICE_SEQUIA\BALANCE1\BH_1975.tif;D:\2026-ARTICULOS\IA-INDICE_SEQUIA\BALANCE1\BH_1976.tif;D:\2026-ARTICULOS\IA-INDICE_SEQUIA\BALANCE1\BH_1977.tif;D:\2026-ARTICULOS\IA-INDICE_SEQUIA\BALANCE1\BH_1978.tif;D:\2026-ARTICULOS\IA-INDICE_SEQUIA\BALANCE1\BH_1979.tif;D:\2026-ARTICULOS\IA-INDICE_SEQUIA\BALANCE1\BH_1980.tif;D:\2026-ARTICULOS\IA-INDICE_SEQUIA\BALANCE1\BH_1981.tif;D:\2026-ARTICULOS\IA-INDICE_SEQUIA\BALANCE1\BH_1982.tif;D:\2026-ARTICULOS\IA-INDICE_SEQUIA\BALANCE1\BH_1983.tif;D:\2026-ARTICULOS\IA-INDICE_SEQUIA\BALANCE1\BH_1984.tif;D:\2026-ARTICULOS\IA-INDICE_SEQUIA\BALANCE1\BH_1985.tif;D:\2026-ARTICULOS\IA-INDICE_SEQUIA\BALANCE1\BH_1986.tif;D:\2026-ARTICULOS\IA-INDICE_SEQUIA\BALANCE1\BH_1987.tif;D:\2026-ARTICULOS\IA-INDICE_SEQUIA\BALANCE1\BH_1988.tif;D:\2026-ARTICULOS\IA-INDICE_SEQUIA\BALANCE1\BH_1989.tif;D:\2026-ARTICULOS\IA-INDICE_SEQUIA\BALANCE1\BH_1990.tif;D:\2026-ARTICULOS\IA-INDICE_SEQUIA\BALANCE1\BH_1991.tif;D:\2026-ARTICULOS\IA-INDICE_SEQUIA\BALANCE1\BH_1992.tif;D:\2026-ARTICULOS\IA-INDICE_SEQUIA\BALANCE1\BH_1993.tif;D:\2026-ARTICULOS\IA-INDICE_SEQUIA\BALANCE1\BH_1994.tif;D:\2026-ARTICULOS\IA-INDICE_SEQUIA\BALANCE1\BH_1995.tif;D:\2026-ARTICULOS\IA-INDICE_SEQUIA\BALANCE1\BH_1996.tif;D:\2026-ARTICULOS\IA-INDICE_SEQUIA\BALANCE1\BH_1997.tif;D:\2026-ARTICULOS\IA-INDICE_SEQUIA\BALANCE1\BH_1998.tif;D:\2026-ARTICULOS\IA-INDICE_SEQUIA\BALANCE1\BH_1999.tif;D:\2026-ARTICULOS\IA-INDICE_SEQUIA\BALANCE1\BH_2000.tif;D:\2026-ARTICULOS\IA-INDICE_SEQUIA\BALANCE1\BH_2001.tif;D:\2026-ARTICULOS\IA-INDICE_SEQUIA\BALANCE1\BH_2002.tif;D:\2026-ARTICULOS\IA-INDICE_SEQUIA\BALANCE1\BH_2003.tif;D:\2026-ARTICULOS\IA-INDICE_SEQUIA\BALANCE1\BH_2004.tif;D:\2026-ARTICULOS\IA-INDICE_SEQUIA\BALANCE1\BH_2005.tif;D:\2026-ARTICULOS\IA-INDICE_SEQUIA\BALANCE1\BH_2006.tif;D:\2026-ARTICULOS\IA-INDICE_SEQUIA\BALANCE1\BH_2007.tif;D:\2026-ARTICULOS\IA-INDICE_SEQUIA\BALANCE1\BH_2008.tif;D:\2026-ARTICULOS\IA-INDICE_SEQUIA\BALANCE1\BH_2009.tif;D:\2026-ARTICULOS\IA-INDICE_SEQUIA\BALANCE1\BH_2010.tif;D:\2026-ARTICULOS\IA-INDICE_SEQUIA\BALANCE1\BH_2011.tif;D:\2026-ARTICULOS\IA-INDICE_SEQUIA\BALANCE1\BH_2012.tif;D:\2026-ARTICULOS\IA-INDICE_SEQUIA\BALANCE1\BH_2013.tif;D:\2026-ARTICULOS\IA-INDICE_SEQUIA\BALANCE1\BH_2014.tif;D:\2026-ARTICULOS\IA-INDICE_SEQUIA\BALANCE1\BH_2015.tif;D:\2026-ARTICULOS\IA-INDICE_SEQUIA\BALANCE1\BH_2016.tif;D:\2026-ARTICULOS\IA-INDICE_SEQUIA\BALANCE1\BH_2017.tif;D:\2026-ARTICULOS\IA-INDICE_SEQUIA\BALANCE1\BH_2018.tif;D:\2026-ARTICULOS\IA-INDICE_SEQUIA\BALANCE1\BH_2019.tif;D:\2026-ARTICULOS\IA-INDICE_SEQUIA\BALANCE1\BH_2020.tif;D:\2026-ARTICULOS\IA-INDICE_SEQUIA\BALANCE1\BH_2021.tif;D:\2026-ARTICULOS\IA-INDICE_SEQUIA\BALANCE1\BH_2022.tif;D:\2026-ARTICULOS\IA-INDICE_SEQUIA\BALANCE1\BH_2023.tif;D:\2026-ARTICULOS\IA-INDICE_SEQUIA\BALANCE1\BH_2024.tif D:\2026-ARTICULOS\IA-INDICE_SEQUIA\MODELO-ML\Balance_mean.tif MEAN DATA</Process></lineage></DataProperties></Esri></metadata>
